MANIFEST.in
README.md
setup.py
dbt/adapters/starrocks/__init__.py
dbt/adapters/starrocks/__version__.py
dbt/adapters/starrocks/column.py
dbt/adapters/starrocks/connections.py
dbt/adapters/starrocks/impl.py
dbt/adapters/starrocks/relation.py
dbt/adapters/starrocks/test.py
dbt/include/starrocks/__init__.py
dbt/include/starrocks/dbt_project.yml
dbt/include/starrocks/profile_template.yml
dbt/include/starrocks/sample_profiles.yml
dbt/include/starrocks/macros/adapters/columns.sql
dbt/include/starrocks/macros/adapters/freshness.sql
dbt/include/starrocks/macros/adapters/metadata.sql
dbt/include/starrocks/macros/adapters/relation.sql
dbt/include/starrocks/macros/adapters/relation_helpers.sql
dbt/include/starrocks/macros/adapters/schema.sql
dbt/include/starrocks/macros/get_custom_name/get_custom_database.sql
dbt/include/starrocks/macros/materializations/hooks.sql
dbt/include/starrocks/macros/materializations/seeds.sql
dbt/include/starrocks/macros/materializations/models/incremental.sql
dbt/include/starrocks/macros/materializations/models/materialized_view.sql
dbt/include/starrocks/macros/materializations/models/table.sql
dbt/include/starrocks/macros/materializations/models/view.sql
dbt/include/starrocks/macros/materializations/snapshot/snapshot.sql
dbt/include/starrocks/macros/materializations/snapshot/snapshot_merge.sql
dbt/include/starrocks/macros/materializations/snapshot/strategies.sql
dbt/include/starrocks/macros/tests/test.sql
dbt/include/starrocks/macros/utils/concat.sql
dbt/include/starrocks/macros/utils/data_types.sql
dbt/include/starrocks/macros/utils/dateadd.sql
dbt/include/starrocks/macros/utils/datediff.sql
dbt_starrocks_klook_data.egg-info/PKG-INFO
dbt_starrocks_klook_data.egg-info/SOURCES.txt
dbt_starrocks_klook_data.egg-info/dependency_links.txt
dbt_starrocks_klook_data.egg-info/not-zip-safe
dbt_starrocks_klook_data.egg-info/requires.txt
dbt_starrocks_klook_data.egg-info/top_level.txt